{
  "imDbId": "tt4934214",
  "title": "Taskmaster",
  "fullTitle": "Taskmaster (TV Series 2015– )",
  "type": "TVSeries",
  "year": "2015",
  "episodes": [
    {
      "id": "tt8046984",
      "seasonNumber": "8",
      "episodeNumber": "1",
      "title": "Hello",
      "image": "https://m.media-amazon.com/images/M/MV5BOWQ5NWI5ZDctYzBlOS00NjAwLWIwOWYtNGM1NWFhY2M0YjIwXkEyXkFqcGdeQXVyNjYyNDMwOQ@@._V1_Ratio1.7778_AL_.jpg",
      "year": "2019",
      "released": "8 May 2019",
      "plot": "The Taskmaster challenges a new set of comedians to compete for his golden head.",
      "imDbRating": "7.7",
      "imDbRatingCount": "174"
    },
    {
      "id": "tt8047808",
      "seasonNumber": "8",
      "episodeNumber": "2",
      "title": "A Novel About Russian Gulags",
      "image": "https://m.media-amazon.com/images/M/MV5BZDIxZjkzYzYtYjkyMS00NGZjLWI1NjUtZDg3Zjc4NzZiMDc4XkEyXkFqcGdeQXVyNjYyNDMwOQ@@._V1_Ratio1.7778_AL_.jpg",
      "year": "2019",
      "released": "15 May 2019",
      "plot": "The competition continues as the Taskmaster judges even more Tasks, including one that Joe Thomas describes as 'dehumanising'.",
      "imDbRating": "7.7",
      "imDbRatingCount": "164"
    },
    {
      "id": "tt8047810",
      "seasonNumber": "8",
      "episodeNumber": "3",
      "title": "Stuck in a Mammal Groove",
      "image": "https://m.media-amazon.com/images/M/MV5BMzhkMWNkYzMtM2Q2YS00NWMzLWFiZGUtMjNiNWUxMzMxYmJlXkEyXkFqcGdeQXVyNjYyNDMwOQ@@._V1_Ratio1.7778_AL_.jpg",
      "year": "2019",
      "released": "22 May 2019",
      "plot": "Can the contestants guess what Alex is dressed as? Can they create a volcano? Most importantly, can they apologize for what they've done?",
      "imDbRating": "7.6",
      "imDbRatingCount": "155"
    },
    {
      "id": "tt10385360",
      "seasonNumber": "8",
      "episodeNumber": "4",
      "title": "The Barrel Dad",
      "image": "https://m.media-amazon.com/images/M/MV5BOTQ3M2JlNzUtMmVmNC00NmZlLTljNjQtNjBmZWEwYjZmNzRjXkEyXkFqcGdeQXVyNjYyNDMwOQ@@._V1_Ratio1.7778_AL_.jpg",
      "year": "2019",
      "released": "29 May 2019",
      "plot": "A hammock-based task threatens to tear the team apart.",
      "imDbRating": "7.7",
      "imDbRatingCount": "155"
    },
    {
      "id": "tt10385362",
      "seasonNumber": "8",
      "episodeNumber": "5",
      "title": "Stay Humble",
      "image": "https://m.media-amazon.com/images/M/MV5BZDNjMjAxMGQtOGRkZC00NDE1LTk4MzYtYTQ1MTg5NmM2NzIwXkEyXkFqcGdeQXVyNjYyNDMwOQ@@._V1_Ratio1.7778_AL_.jpg",
      "year": "2019",
      "released": "5 Jun. 2019",
      "plot": "Herding ping-pong balls, playing catch around the globe and creating food-based injuries are just three of the tasks on offer as the show reaches its halfway point.",
      "imDbRating": "7.6",
      "imDbRatingCount": "150"
    },
    {
      "id": "tt10385364",
      "seasonNumber": "8",
      "episodeNumber": "6",
      "title": "Rock 'n' Roll Umlaut",
      "image": "https://m.media-amazon.com/images/M/MV5BNDJmMTYyZDctYmI0Ni00YTRlLWFhNGMtYjEyZDQ4MmQ3NjJkXkEyXkFqcGdeQXVyNjYyNDMwOQ@@._V1_Ratio1.7937_AL_.jpg",
      "year": "2019",
      "released": "12 Jun. 2019",
      "plot": "This week, the comedians are challenged with designing an album cover, scoring a goal, remembering the order of some very special playing cards and hiding in a phone-box.",
      "imDbRating": "7.7",
      "imDbRatingCount": "148"
    },
    {
      "id": "tt8047818",
      "seasonNumber": "8",
      "episodeNumber": "7",
      "title": "This Is Trevor",
      "image": "https://m.media-amazon.com/images/M/MV5BMzlmYjVjN2YtOTk1OC00MDY2LTgxZTEtZWE1NzYwZWNlODJhXkEyXkFqcGdeQXVyNjYyNDMwOQ@@._V1_Ratio1.7778_AL_.jpg",
      "year": "2019",
      "released": "19 Jun. 2019",
      "plot": "Can the contestants pick the Pink Ladies? Can they do something powerful with their pinkies? The taskmaster intends to find out.",
      "imDbRating": "7.7",
      "imDbRatingCount": "144"
    },
    {
      "id": "tt8047822",
      "seasonNumber": "8",
      "episodeNumber": "8",
      "title": "Aquatic Sewing Machine",
      "image": "https://m.media-amazon.com/images/M/MV5BY2Y2NjNiYWEtNTQyOS00M2UyLWE1OTQtMGMyZTdiMTRjZWY5XkEyXkFqcGdeQXVyNjYyNDMwOQ@@._V1_Ratio1.7778_AL_.jpg",
      "year": "2019",
      "released": "26 Jun. 2019",
      "plot": "The taskmaster imagines an aquatic trauma when the contestants are asked to bring in the best thing to hold, before an underdog begins to rise through the ranks as the word-based final task approaches.",
      "imDbRating": "7.9",
      "imDbRatingCount": "151"
    },
    {
      "id": "tt8047824",
      "seasonNumber": "8",
      "episodeNumber": "9",
      "title": "I've Been a Bit Ill",
      "image": "https://m.media-amazon.com/images/M/MV5BMTEzMjM1NGYtMTE0Ny00MmI4LTkzMWQtNGQzODVkOWQ4YmI0XkEyXkFqcGdeQXVyNjYyNDMwOQ@@._V1_Ratio1.7778_AL_.jpg",
      "year": "2019",
      "released": "3 Jul. 2019",
      "plot": "The penultimate episode sees the formation of some very strange new people.",
      "imDbRating": "7.8",
      "imDbRatingCount": "142"
    },
    {
      "id": "tt8047826",
      "seasonNumber": "8",
      "episodeNumber": "10",
      "title": "Clumpy Swayey Clumsy Man",
      "image": "https://m.media-amazon.com/images/M/MV5BNjBlZWEzMGQtNmEyNS00M2Q3LTg3ZDgtZWVmNWQ5YmI2NjhkXkEyXkFqcGdeQXVyNjYyNDMwOQ@@._V1_Ratio1.7778_AL_.jpg",
      "year": "2019",
      "released": "10 Jul. 2019",
      "plot": "Who will take home the coveted 'golden head' trophy in the Taskmaster series 8 finale?",
      "imDbRating": "8.1",
      "imDbRatingCount": "147"
    }
  ],
  "errorMessage": ""
}