{
  "id": "tt3230908",
  "title": "Mizumono",
  "originalTitle": "",
  "fullTitle": "Mizumono (TV Episode 2014)",
  "type": "TVEpisode",
  "year": "2014",
  "image": "https://m.media-amazon.com/images/M/MV5BMjEyNzM1NDg1N15BMl5BanBnXkFtZTgwNDAwMzE4MTE@._V1_Ratio1.5018_AL_.jpg",
  "releaseDate": "2014-05-23",
  "runtimeMins": "44",
  "runtimeStr": "44min",
  "plot": "Jack devises a plan to apprehend Hannibal, while Hannibal prepares for his departure. Will makes his decision, and it results in devastating consequences.",
  "plotLocal": "",
  "plotLocalIsRtl": false,
  "awards": "",
  "directors": "David Slade",
  "directorList": [
    {
      "id": "nm1720541",
      "name": "David Slade"
    }
  ],
  "writers": "Bryan Fuller, Thomas Harris, Steve Lightfoot",
  "writerList": [
    {
      "id": "nm0298188",
      "name": "Bryan Fuller"
    },
    {
      "id": "nm0365383",
      "name": "Thomas Harris"
    },
    {
      "id": "nm1208415",
      "name": "Steve Lightfoot"
    }
  ],
  "stars": "Hugh Dancy, Mads Mikkelsen, Caroline Dhavernas",
  "starList": [
    {
      "id": "nm0199215",
      "name": "Hugh Dancy"
    },
    {
      "id": "nm0586568",
      "name": "Mads Mikkelsen"
    },
    {
      "id": "nm0223518",
      "name": "Caroline Dhavernas"
    }
  ],
  "actorList": [
    {
      "id": "nm0199215",
      "image": "https://m.media-amazon.com/images/M/MV5BMTUzNTgxMDM2OV5BMl5BanBnXkFtZTcwMTQ1Mzc3Mg@@._V1_Ratio1.0000_AL_.jpg",
      "name": "Hugh Dancy",
      "asCharacter": "Will Graham"
    },
    {
      "id": "nm0586568",
      "image": "https://m.media-amazon.com/images/M/MV5BMTcyMTU5MzgxMF5BMl5BanBnXkFtZTYwMDI0NjI1._V1_Ratio1.0000_AL_.jpg",
      "name": "Mads Mikkelsen",
      "asCharacter": "Dr. Hannibal Lecter"
    },
    {
      "id": "nm0223518",
      "image": "https://m.media-amazon.com/images/M/MV5BMTk2OTU5ODY4Ml5BMl5BanBnXkFtZTcwNjQ1MTgyMQ@@._V1_Ratio1.0000_AL_.jpg",
      "name": "Caroline Dhavernas",
      "asCharacter": "Dr. Alana Bloom"
    },
    {
      "id": "nm0000401",
      "image": "https://m.media-amazon.com/images/M/MV5BMTc0NjczNDc1MV5BMl5BanBnXkFtZTYwMDU0Mjg1._V1_Ratio1.0000_AL_.jpg",
      "name": "Laurence Fishburne",
      "asCharacter": "Jack Crawford"
    },
    {
      "id": "nm0633223",
      "image": "https://m.media-amazon.com/images/M/MV5BMjIxNzgxMDU4OV5BMl5BanBnXkFtZTcwOTM3MTU5MQ@@._V1_Ratio1.0000_AL_.jpg",
      "name": "Cynthia Nixon",
      "asCharacter": "Kade Prurnell"
    },
    {
      "id": "nm0868659",
      "image": "https://m.media-amazon.com/images/M/MV5BMGEzNzg0YmUtNDEwZi00NGRkLWE2MGMtYWU0ZTY5YWNhNGNjXkEyXkFqcGdeQXVyNjU0ODA3OTg@._V1_Ratio1.0000_AL_.jpg",
      "name": "Gina Torres",
      "asCharacter": "Bella Crawford"
    },
    {
      "id": "nm1892299",
      "image": "https://m.media-amazon.com/images/M/MV5BNTNkMTcxYjYtYjBlZS00OWNiLWIyNTQtN2UwMjIzODU2MjhmXkEyXkFqcGdeQXVyMjAyNzk0MjY@._V1_Ratio1.0000_AL_.jpg",
      "name": "Lara Jean Chorostecki",
      "asCharacter": "Freddie Lounds"
    },
    {
      "id": "nm3821782",
      "image": "https://m.media-amazon.com/images/M/MV5BYTQ3NTIxN2YtMzc0YS00ZDE4LWE1N2QtZDAyZDc1ZWRlOGNmXkEyXkFqcGdeQXVyMDM2NDM2MQ@@._V1_Ratio1.0000_AL_.jpg",
      "name": "Kacey Rohl",
      "asCharacter": "Abigail Hobbs"
    },
    {
      "id": "nm0190938",
      "image": "https://m.media-amazon.com/images/M/MV5BZDg5MGJkNjMtM2IxMC00MGVhLTlkMzEtOThjMWQ5NzQyN2NhXkEyXkFqcGdeQXVyMjQwMDg0Ng@@._V1_Ratio1.0857_AL_.jpg",
      "name": "Vladimir Jon Cubrt",
      "asCharacter": "Garret Jacob Hobbs"
    },
    {
      "id": "nm0000096",
      "image": "https://m.media-amazon.com/images/M/MV5BMmRjNWQwMDQtMWNjZS00ZTUzLTkwODEtMTU5YjRlZmJiMTVkXkEyXkFqcGdeQXVyMTEzNjc3MDQ5._V1_Ratio1.0000_AL_.jpg",
      "name": "Gillian Anderson",
      "asCharacter": "Dr. Bedelia Du Maurier"
    },
    {
      "id": "nm0539767",
      "image": "https://m.media-amazon.com/images/M/MV5BOTIyNzE5ODQtZmRiNC00MDc5LWJmNGQtM2FjZTNiMDk0NDFjXkEyXkFqcGdeQXVyODQxMjkyNQ@@._V1_Ratio1.0000_AL_.jpg",
      "name": "Jessica Malka",
      "asCharacter": "French Stewardess"
    }
  ],
  "fullCast": null,
  "genres": "Crime, Drama, Horror",
  "genreList": [
    {
      "key": "Crime",
      "value": "Crime"
    },
    {
      "key": "Drama",
      "value": "Drama"
    },
    {
      "key": "Horror",
      "value": "Horror"
    }
  ],
  "companies": "Dino De Laurentiis Company, Living Dead Guy Productions, AXN: Original X Production",
  "companyList": [
    {
      "id": "co0014380",
      "name": "Dino De Laurentiis Company"
    },
    {
      "id": "co0138108",
      "name": "Living Dead Guy Productions"
    },
    {
      "id": "co0368304",
      "name": "AXN: Original X Production"
    }
  ],
  "countries": "",
  "countryList": [],
  "languages": "English",
  "languageList": [
    {
      "key": "English",
      "value": "English"
    }
  ],
  "contentRating": "TV-14",
  "imDbRating": "9.8",
  "imDbRatingVotes": "20355",
  "metacriticRating": null,
  "ratings": null,
  "wikipedia": null,
  "posters": null,
  "images": null,
  "trailer": null,
  "boxOffice": {
    "budget": "",
    "openingWeekendUSA": "",
    "grossUSA": "",
    "cumulativeWorldwideGross": ""
  },
  "tagline": null,
  "keywords": "stabbing,fight in a kitchen,flying first class,stabbed in the belly,throat cut",
  "keywordList": [
    "stabbing",
    "fight in a kitchen",
    "flying first class",
    "stabbed in the belly",
    "throat cut"
  ],
  "similars": [],
  "tvSeriesInfo": null,
  "tvEpisodeInfo": {
    "seriesId": "tt2243973",
    "seriesTitle": "Hannibal",
    "seriesFullTitle": "Hannibal (TV Series 2013–2015)",
    "seriesYear": "2013",
    "seriesYearEnd": "2015",
    "seasonNumber": "2",
    "episodeNumber": "13",
    "previousEpisodeId": "tt3230910",
    "nextEpisodeId": "tt3724578"
  },
  "errorMessage": ""
}